hkjc/__init__.py
hkjc/features.py
hkjc/harville_model.py
hkjc/historical.py
hkjc/live.py
hkjc/processing.py
hkjc/py.typed
hkjc/speedpro.py
hkjc/utils.py
hkjc/strategy/place_only.py
hkjc/strategy/qpbanker.py
hkjc-0.4.1.dist-info/METADATA
hkjc-0.4.1.dist-info/WHEEL
hkjc-0.4.1.dist-info/RECORD
