Metadata-Version: 2.4
Name: hkjc
Version: 0.4.1
Summary: Library for scrapping HKJC data and perform basic analysis
Requires-Python: >=3.11
Requires-Dist: beautifulsoup4>=4.14.2
Requires-Dist: cachetools>=6.2.0
Requires-Dist: fastexcel>=0.16.0
Requires-Dist: flask>=3.1.2
Requires-Dist: numba>=0.62.1
Requires-Dist: numpy>=2.3.3
Requires-Dist: polars>=1.33.1
Requires-Dist: pyarrow>=21.0.0
Requires-Dist: requests>=2.32.5
Requires-Dist: scipy>=1.16.2
Requires-Dist: tqdm>=4.67.1
